[
  {
    "id": 145,
    "name": "SanJuan City",
    "imageUrl": "https://raw.githubusercontent.com/Dennis1233/seth/master/4.PNG",
    "price": 90,
    "priceCurrency": "PESO",
    "lat": 16.671967,
    "lng": 120.362758
  },
  {
    "id": 148,
    "name": "Hundred Island",
    "imageUrl": "https://raw.githubusercontent.com/Dennis1233/seth/master/a.jpg",
    "price": 200,
    "priceCurrency": "PESO",
    "lat": 16.204001,
    "lng": 120.040869
  },
  {
    "id": 201,
    "name": "Puerto Princesa Underground River",
    "imageUrl": "https://raw.githubusercontent.com/Dennis1233/seth/master/b.jpg",
    "price": 150,
    "priceCurrency": "PESO",
    "lat": 10.192559,
    "lng": 118.926583
  },
  {
    "id": 205,
    "name": "Chocolate Hills",
    "imageUrl": "https://raw.githubusercontent.com/Dennis1233/seth/master/c.jpg",
    "price": 115,
    "priceCurrency": "PESO",
    "lat": 9.829708,
    "lng": 124.139676
  },
  {
    "id": 210,
    "name": "Rice Terraces",
    "imageUrl": "https://raw.githubusercontent.com/Dennis1233/seth/master/d.jpg",
    "price": 135,
    "priceCurrency": "PESO",
    "lat": 16.923954,
    "lng": 121.055640
  },
  {
    "id": 211,
    "name": "El Nido Palawan",
    "imageUrl": "https://raw.githubusercontent.com/Dennis1233/seth/master/e.jpg",
    "price": 90,
    "priceCurrency": "PESO",
    "lat": 11.209709,
    "lng": 119.462254
  },
  {
    "id": 212,
    "name": "Vigan",
    "imageUrl": "https://raw.githubusercontent.com/Dennis1233/seth/master/f.jpg",
    "price": 135,
    "priceCurrency": "PESO",
    "lat": 17.570490,
    "lng": 120.387330
     },
  {
    "id": 213,
    "name": "Camiguin",
    "imageUrl": "https://github.com/Dennis1233/seth/blob/master/g.jpg",
    "price": 135,
    "priceCurrency": "PESO",
    "lat": 9.173216,
    "lng": 124.729877
  }
]
